[
  {
    "name": "castlemap",
    "location_size": 40,
    "location_border_thickness": 5,
    "img": "images/CastleMap.png"
  },
  {
    "name": "cityofhazemap",
    "location_size": 40,
    "location_border_thickness": 5,
    "img": "images/CityOfHazeMap.png"
  },
  {
    "name": "sandygravemap",
    "location_size": 40,
    "location_border_thickness": 5,
    "img": "images/SandyGraveMap.png"
  },
  {
    "name": "nationoffoolsmap",
    "location_size": 40,
    "location_border_thickness": 5,
    "img": "images/NationOfFoolsMap.png"
  },
  {
    "name": "forestofdoommap",
    "location_size": 40,
    "location_border_thickness": 5,
    "img": "images/ForestOfDoomMap.png"
  },
  {
    "name": "darkacademymap",
    "location_size": 40,
    "location_border_thickness": 5,
    "img": "images/DarkAcademyMap.png"
  },
  {
    "name": "forgottencitymap",
    "location_size": 40,
    "location_border_thickness": 5,
    "img": "images/ForgottenCityMap.png"
  },
  {
    "name": "burntparadisemap",
    "location_size": 40,
    "location_border_thickness": 5,
    "img": "images/BurntParadiseMap.png"
  },
  {
    "name": "13thstreetmap",
    "location_size": 40,
    "location_border_thickness": 5,
    "img": "images/13thStreetMap.png"
  }
]
